vrc_controller/__init__.py
vrc_controller/constants.py
vrc_controller/osc.py
vrc_controller/singletons.py
vrc_controller/sounds.py
vrc_controller-0.0.1.dist-info/LICENSE.md
vrc_controller-0.0.1.dist-info/METADATA
vrc_controller-0.0.1.dist-info/WHEEL
vrc_controller-0.0.1.dist-info/top_level.txt
vrc_controller-0.0.1.dist-info/RECORD
